syak.py
syak-0.1.9.dist-info/LICENSE
syak-0.1.9.dist-info/WHEEL
syak-0.1.9.dist-info/entry_points.txt
syak-0.1.9.dist-info/METADATA
syak-0.1.9.dist-info/RECORD
