Metadata-Version: 2.1
Name: syak
Version: 0.1.9
Summary: SiYuan sync to Anki
Home-page: https://github.com/why8023/SYAK
License: MIT
Keywords: Anki,SiYuan
Author: why8023
Author-email: whyniaaa@gmail.com
Requires-Python: >=3.9,<4.0
Classifier: License :: OSI Approved :: MIT License
Classifier: Programming Language :: Python :: 3
Classifier: Programming Language :: Python :: 3.9
Classifier: Programming Language :: Python :: 3.10
Classifier: Programming Language :: Python :: 3.11
Requires-Dist: markdown2 (>=2.4.6,<3.0.0)
Requires-Dist: pandas (>=1.5.2,<2.0.0)
Requires-Dist: psutil (>=5.9.0,<6.0.0)
Requires-Dist: requests (>=2.28.1,<3.0.0)
Requires-Dist: schedule (>=1.1.0,<2.0.0)
Project-URL: Documentation, https://github.com/why8023/SYAK
Project-URL: Repository, https://github.com/why8023/SYAK
